HISTORY.rst
MANIFEST.in
README.rst
setup.py
py_bingads/__init__.py
py_bingads/_constants.py
py_bingads/_utils.py
py_bingads.egg-info/PKG-INFO
py_bingads.egg-info/SOURCES.txt
py_bingads.egg-info/dependency_links.txt
py_bingads.egg-info/requires.txt
py_bingads.egg-info/top_level.txt
py_bingads/models/__init__.py
py_bingads/models/account.py
py_bingads/models/ad.py
py_bingads/models/ad_extension.py
py_bingads/models/ad_extension_association.py
py_bingads/models/ad_extension_id_to_entity_id_association.py
py_bingads/models/ad_extension_identity.py
py_bingads/models/ad_group.py
py_bingads/models/callout_ad_extension.py
py_bingads/models/campaign.py
py_bingads/models/keyword.py
py_bingads/models/long.py
py_bingads/models/negative_keyword.py
py_bingads/models/negative_keyword_list.py
py_bingads/models/review_ad_extension.py
py_bingads/models/shared_entity.py
py_bingads/models/shared_entity_association.py
py_bingads/models/shared_list.py
py_bingads/models/shared_list_item.py
py_bingads/models/sitelink_2_ad_extension.py
py_bingads/services/__init__.py
py_bingads/services/ad_extensions.py
py_bingads/services/ad_groups.py
py_bingads/services/base.py
py_bingads/services/callouts.py
py_bingads/services/campaigns.py
py_bingads/services/negative_keywords.py
py_bingads/services/reviews.py
py_bingads/services/sitelinks.py