Metadata-Version: 1.1
Name: py-bingads
Version: 0.1.0
Summary: Wraps BingAds Python SDK to make it more Pythonic
Home-page: https://github.com/stylight/python-bingads
Author: Julie MacDonell
Author-email: julie.macdonell@stylight.com
License: MIT License
Download-URL: https://github.com/stylight/python-bingads/archive/0.2.tar.gz
Keywords: python bingads bing ads api
Platform: UNKNOWN
